bdocs/__init__.py
bdocs/bdocs.py
bdocs/bdocs_config.py
bdocs/block.py
bdocs/brepl.py
bdocs/building_docs.py
bdocs/building_metadata.py
bdocs/deleter.py
bdocs/file_util.py
bdocs/git/git_deleter.py
bdocs/git/git_mover.py
bdocs/git/git_rooter.py
bdocs/git/git_util.py
bdocs/git/git_writer.py
bdocs/indexer.py
bdocs/mover.py
bdocs/multi_building_docs.py
bdocs/printer.py
bdocs/root_info.py
bdocs/rooter.py
bdocs/rotater.py
bdocs/rules/rule.py
bdocs/rules/rule_types.py
bdocs/rules/rules.py
bdocs/search/index.py
bdocs/search/index_doc.py
bdocs/search/whoosh_index.py
bdocs/search/whoosh_indexer.py
bdocs/search/whoosh_searcher.py
bdocs/search_options.py
bdocs/searcher.py
bdocs/simple_deleter.py
bdocs/simple_mover.py
bdocs/simple_null_indexer.py
bdocs/simple_null_searcher.py
bdocs/simple_null_transformer.py
bdocs/simple_rooter.py
bdocs/simple_rotater.py
bdocs/simple_walker.py
bdocs/simple_writer.py
bdocs/simple_zipper.py
bdocs/tree_util.py
bdocs/user.py
bdocs/walker.py
bdocs/writer.py
bdocs/zipper.py
bdocs-0.0.0.2.dist-info/METADATA
bdocs-0.0.0.2.dist-info/WHEEL
bdocs-0.0.0.2.dist-info/RECORD
