Metadata-Version: 2.1
Name: bdocs
Version: 0.0.0.2
Summary: A library to provide modify methods and higher features to Cdocs.
Author: David Kershaw
Author-email: dk107dk@hotmail.com
Requires-Python: >=3.12,<4.0
Classifier: Environment :: Console
Classifier: Programming Language :: Python :: 3
Classifier: Programming Language :: Python :: 3.12
Classifier: Topic :: Documentation
Classifier: Topic :: Text Processing :: Markup
Requires-Dist: cdocs (==0.0.42)
Requires-Dist: dulwich (>=0.21.7,<0.22.0)
Requires-Dist: whoosh (>=2.7.4,<3.0.0)
Project-URL: Github, https://github.com/dk107dk/bdocs
